cachium/__init__.py
cachium/_decorators.py
cachium/_errors.py
cachium/_helpers.py
cachium/logger.py
cachium/py.typed
cachium/key_builders/__init__.py
cachium/key_builders/_abc.py
cachium/key_builders/_default.py
cachium/serializers/__init__.py
cachium/serializers/_abc.py
cachium/serializers/_md5.py
cachium/serializers/_repr.py
cachium/serializers/_std_hash.py
cachium/serializers/_str.py
cachium/storages/__init__.py
cachium/storages/_abc.py
cachium/storages/ttl_map.py
cachium-0.0.1a1.dist-info/METADATA
cachium-0.0.1a1.dist-info/WHEEL
cachium-0.0.1a1.dist-info/licenses/LICENSE
cachium-0.0.1a1.dist-info/RECORD
