Metadata-Version: 2.4
Name: cachium
Version: 0.0.1a1
Summary: Sync and async cache with TTL and LRU support.
Project-URL: Changelog, https://github.com/zoola969/cachium/CHANGELOG.md
Project-URL: Documentation, https://cachium.readthedocs.io/en/latest/
Project-URL: Homepage, https://github.com/zoola969/cachium
Project-URL: Issues, https://github.com/zoola969/cachium/issues
Project-URL: Repository, https://github.com/zoola969/cachium.git
Author-email: Alexander Dmitriev <zoola969@gmail.com>
License:                                  Apache License
License-File: LICENSE
Keywords: cache,lru,lru-cache,time-to-live,ttl
Classifier: Development Status :: 4 - Beta
Classifier: Intended Audience :: Developers
Classifier: License :: OSI Approved :: Apache Software License
Classifier: Operating System :: OS Independent
Classifier: Programming Language :: Python
Classifier: Programming Language :: Python :: 3
Classifier: Programming Language :: Python :: 3.9
Classifier: Programming Language :: Python :: 3.10
Classifier: Programming Language :: Python :: 3.11
Classifier: Programming Language :: Python :: 3.12
Classifier: Programming Language :: Python :: 3.13
Classifier: Topic :: Software Development :: Libraries
Classifier: Typing :: Typed
Requires-Python: >=3.9
Requires-Dist: ttlru-map~=1.1
Requires-Dist: typing-extensions~=4.0
